pyautoflip/__init__.py
pyautoflip/cli.py
pyautoflip/core/__init__.py
pyautoflip/core/processor.py
pyautoflip/cropping/__init__.py
pyautoflip/cropping/camera_motion.py
pyautoflip/cropping/detection_utils.py
pyautoflip/cropping/frame_crop_region.py
pyautoflip/cropping/padding_effects.py
pyautoflip/cropping/scene_cropper.py
pyautoflip/cropping/types.py
pyautoflip/detection/__init__.py
pyautoflip/detection/blaze_face_short_range.tflite
pyautoflip/detection/efficientdet_lite0.tflite
pyautoflip/detection/face_detector.py
pyautoflip/detection/mediapipe_face_detector.py
pyautoflip/detection/mediapipe_object_detector.py
pyautoflip/detection/shot_boundary.py
pyautoflip/utils/__init__.py
pyautoflip/utils/video.py
pyautoflip/utils/visualizer.py
pyautoflip-0.1.1.dist-info/METADATA
pyautoflip-0.1.1.dist-info/WHEEL
pyautoflip-0.1.1.dist-info/entry_points.txt
pyautoflip-0.1.1.dist-info/licenses/LICENSE
pyautoflip-0.1.1.dist-info/RECORD
