Metadata-Version: 2.4
Name: pyautoflip
Version: 0.1.1
Summary: Intelligent video reframing library that automatically crops videos to different aspect ratios while preserving important content using AI
Project-URL: Homepage, https://github.com/AhmedHisham1/pyautoflip
Project-URL: Repository, https://github.com/AhmedHisham1/pyautoflip
Project-URL: Documentation, https://github.com/AhmedHisham1/pyautoflip#readme
Author-email: Ahmed Hisham <a7med.hish@gmail.com>
License: MIT
License-File: LICENSE
Keywords: aspect-ratio,autoflip,computer-vision,cropping,face-detection,object-detection,reframing,video
Classifier: Development Status :: 4 - Beta
Classifier: Intended Audience :: Developers
Classifier: Intended Audience :: End Users/Desktop
Classifier: License :: OSI Approved :: MIT License
Classifier: Operating System :: OS Independent
Classifier: Programming Language :: Python :: 3
Classifier: Programming Language :: Python :: 3.10
Classifier: Programming Language :: Python :: 3.11
Classifier: Programming Language :: Python :: 3.12
Classifier: Programming Language :: Python :: 3.13
Classifier: Topic :: Multimedia :: Video
Classifier: Topic :: Multimedia :: Video :: Conversion
Classifier: Topic :: Scientific/Engineering :: Artificial Intelligence
Classifier: Topic :: Scientific/Engineering :: Image Processing
Requires-Python: <3.14,>=3.10
Requires-Dist: insightface>=0.7.3
Requires-Dist: mediapipe>=0.10.21
Requires-Dist: numpy>=1.24.0
Requires-Dist: onnxruntime>=1.21.0
Requires-Dist: opencv-python>=4.11.0.86
Requires-Dist: pillow>=10.0.0
Requires-Dist: scenedetect>=0.6.6
Requires-Dist: scikit-learn>=1.6.1
Requires-Dist: tqdm>=4.65.0
